<?xml version="1.0" encoding="UTF-8"?>
<templateSet group="Py-Cord">

    <!-- Bot Main -->
    <template name="ez-main" value="import discord&#10;import ezcord&#10;&#10;class Bot(ezcord.Bot):&#10;    def __init__(self):&#10;        super().__init__(intents=discord.Intents.$INTENTS$(), language=&quot;$LANGUAGE$&quot;)&#10;&#10;        self.load_cogs()&#10;        self.add_help_command()&#10;        self.add_status_changer(&#10;            &quot;$STATUS_TEXT$&quot;,&#10;            discord.Game(&quot;$GAME_TEXT$&quot;),&#10;        )&#10;&#10;&#10;if __name__ == &quot;__main__&quot;:&#10;    bot = Bot()&#10;    bot.run()&#10;$END$" description="[py-cord] Main with ezcord" toReformat="true" toShortenFQNames="true">
        <variable name="INTENTS" expression="" defaultValue="&quot;default&quot;" alwaysStopAt="true" />
        <variable name="LANGUAGE" expression="" defaultValue="&quot;en&quot;" alwaysStopAt="true" />
        <variable name="STATUS_TEXT" expression="" defaultValue="&quot;Ezcord&quot;" alwaysStopAt="true" />
        <variable name="GAME_TEXT" expression="" defaultValue="&quot;on {guild_count} servers&quot;" alwaysStopAt="true" />
        <context>
            <option name="Python" value="true" />
        </context>
    </template>

    <!-- Cog Template -->
    <template name="ez-cog" value="import discord&#10;import ezcord&#10;from discord.commands import slash_command&#10;&#10;&#10;class $COG_NAME$(ezcord.Cog, emoji=&quot;$EMOJI$&quot;):&#10;    def __init__(self, bot: ezcord.Bot):&#10;        self.bot = bot&#10;    &#10;    @slash_command(description=&quot;$DESCRIPTION$&quot;)&#10;    async def $COMMAND_NAME$(self, ctx: discord.ApplicationContext):&#10;        await ctx.respond(&quot;$RESPONSE$&quot;)&#10;&#10;&#10;def setup(bot: ezcord.Bot):&#10;    bot.add_cog($COG_NAME$(bot))&#10;$END$" description="[py-cord] Cog with ezcord" toReformat="true" toShortenFQNames="true">
        <variable name="COG_NAME" expression="" defaultValue="&quot;Base&quot;" alwaysStopAt="true" />
        <variable name="EMOJI" expression="" defaultValue="&quot;ðŸ‘‹ðŸ¼&quot;" alwaysStopAt="true" />
        <variable name="COMMAND_NAME" expression="" defaultValue="&quot;hey&quot;" alwaysStopAt="true" />
        <variable name="DESCRIPTION" expression="" defaultValue="&quot;Say hello!&quot;" alwaysStopAt="true" />
        <variable name="RESPONSE" expression="" defaultValue="&quot;Hello Everyone!&quot;" alwaysStopAt="true" />
        <context>
            <option name="Python" value="true" />
        </context>
    </template>

    <!-- Button Template -->
    <template name="ez-button" value="class $BUTTON_NAME$(discord.ui.Button):&#10;    def __init__(self):&#10;        super().__init__(label=&quot;$LABEL$&quot;, emoji=&quot;$EMOJI$&quot;, style=discord.ButtonStyle.$STYLE$)&#10;&#10;    async def callback(self, interaction: ezcord.EzContext):&#10;        await interaction.respond(f&quot;$RESPONSE$&quot;)&#10;$END$" description="[py-cord] Button with ezcord" toReformat="true" toShortenFQNames="true">
        <variable name="BUTTON_NAME" expression="" defaultValue="&quot;Button&quot;" alwaysStopAt="true" />
        <variable name="LABEL" expression="" defaultValue="&quot;Welcome&quot;" alwaysStopAt="true" />
        <variable name="EMOJI" expression="" defaultValue="&quot;ðŸ‘‹ðŸ¼&quot;" alwaysStopAt="true" />
        <variable name="STYLE" expression="" defaultValue="&quot;gray&quot;" alwaysStopAt="true" />
        <variable name="RESPONSE" expression="" defaultValue="&quot;ðŸ‘‹ðŸ¼ Welcome {interaction.user.name}!&quot;" alwaysStopAt="true" />
        <context>
            <option name="Python" value="true" />
        </context>
    </template>

    <!-- Modal Template -->
    <template name="ez-modal" value="class $MODAL_NAME$(discord.ui.DesignerModal):&#10;    def __init__(self):&#10;        super().__init__(&#10;            discord.ui.Label(&#10;                &quot;$LABEL_TEXT$&quot;,&#10;                discord.ui.InputText(&#10;                    placeholder=&quot;$PLACEHOLDER$&quot;,&#10;                    required=$REQUIRED$,&#10;                ),&#10;                description=&quot;$DESCRIPTION$&quot;,&#10;            ),&#10;            title=&quot;$TITLE$&quot;&#10;        )&#10;&#10;    async def callback(self, interaction: ezcord.EzContext):&#10;        typed = self.children[0].item.value&#10;        await interaction.respond(f&quot;$RESPONSE$&quot;)&#10;$END$" description="[py-cord] Modal with ezcord" toReformat="true" toShortenFQNames="true">
        <variable name="MODAL_NAME" expression="" defaultValue="&quot;Modal&quot;" alwaysStopAt="true" />
        <variable name="LABEL_TEXT" expression="" defaultValue="&quot;Label&quot;" alwaysStopAt="true" />
        <variable name="PLACEHOLDER" expression="" defaultValue="&quot;This is a placeholder&quot;" alwaysStopAt="true" />
        <variable name="REQUIRED" expression="" defaultValue="True" alwaysStopAt="true" />
        <variable name="DESCRIPTION" expression="" defaultValue="&quot;This is a description&quot;" alwaysStopAt="true" />
        <variable name="TITLE" expression="" defaultValue="&quot;Just a Title&quot;" alwaysStopAt="true" />
        <variable name="RESPONSE" expression="" defaultValue="&quot;You typed: {typed}&quot;" alwaysStopAt="true" />
        <context>
            <option name="Python" value="true" />
        </context>
    </template>

    <!-- Select Template -->
    <template name="ez-select" value="class $SELECT_NAME$(discord.ui.Select):&#10;    def __init__(self):&#10;&#10;        options = []&#10;&#10;        super().__init__(&#10;            placeholder=&quot;$PLACEHOLDER$&quot;,&#10;            options=options,&#10;            required=$REQUIRED$&#10;        )&#10;&#10;    async def callback(self, interaction: ezcord.EzContext):&#10;        selected = self.values[0]&#10;        await interaction.respond(f&quot;$RESPONSE$&quot;)&#10;$END$" description="[py-cord] Select with ezcord" toReformat="true" toShortenFQNames="true">
        <variable name="SELECT_NAME" expression="" defaultValue="&quot;Select&quot;" alwaysStopAt="true" />
        <variable name="PLACEHOLDER" expression="" defaultValue="&quot;This is a Select&quot;" alwaysStopAt="true" />
        <variable name="REQUIRED" expression="" defaultValue="True" alwaysStopAt="true" />
        <variable name="RESPONSE" expression="" defaultValue="&quot;You selected: {selected}&quot;" alwaysStopAt="true" />
        <context>
            <option name="Python" value="true" />
        </context>
    </template>

</templateSet>